{
  "categories": {
    "Politics": ["election", "government", "president", "minister", "parliament", "vote", "campaign", "political", "democracy", "diplomatic"],
    "War & Conflict": ["war", "military", "attack", "bombing", "conflict", "battle", "soldiers", "weapons", "missile", "invasion", "siege", "killed", "forces", "combat", "strike", "casualties", "troops", "armed", "violence", "death", "shooting", "cease-fire", "hostilities"],
    "Terrorism": ["terror", "terrorist", "extremist", "bomb", "suicide", "radical", "jihadist", "isis", "al-qaeda"],
    "Natural Disasters": ["earthquake", "tsunami", "hurricane", "typhoon", "flood", "wildfire", "volcano", "drought", "storm", "landslide"],
    "Economy": ["economy", "trade", "market", "business", "financial", "currency", "inflation", "unemployment", "gdp", "stock"],
    "Health": ["health", "medical", "hospital", "disease", "pandemic", "covid", "virus", "vaccine", "outbreak", "doctor"],
    "Crime": ["murder", "robbery", "kidnapping", "arrest", "police", "crime", "criminal", "prison", "court", "trial"],
    "Sports": ["olympics", "world cup", "football", "soccer", "basketball", "tennis", "sports", "athlete", "championship", "tournament"],
    "Technology": ["technology", "ai", "artificial intelligence", "internet", "cyber", "digital", "tech", "innovation", "startup", "algorithm"],
    "Environment": ["climate", "environment", "pollution", "carbon", "renewable", "sustainability", "green", "emissions", "global warming"],
    "Social Issues": ["protest", "demonstration", "rights", "justice", "equality", "discrimination", "racism", "gender", "lgbtq", "immigration"]
  },
  "countries": {
    "korea": "South Korea",
    "korean": "South Korea",
    "china": "China",
    "chinese": "China",
    "japan": "Japan",
    "japanese": "Japan",
    "russia": "Russia",
    "russian": "Russia",
    "ukraine": "Ukraine",
    "ukrainian": "Ukraine",
    "israel": "Israel",
    "israeli": "Israel",
    "palestine": "Palestine",
    "palestinian": "Palestine",
    "gaza": "Palestine",
    "west bank": "Palestine",
    "iran": "Iran",
    "iranian": "Iran",
    "syria": "Syria",
    "syrian": "Syria",
    "iraq": "Iraq",
    "iraqi": "Iraq",
    "afghanistan": "Afghanistan",
    "afghan": "Afghanistan",
    "turkey": "Turkey",
    "turkish": "Turkey",
    "india": "India",
    "indian": "India",
    "pakistan": "Pakistan",
    "pakistani": "Pakistan",
    "bangladesh": "Bangladesh",
    "bengali": "Bangladesh",
    "myanmar": "Myanmar",
    "burma": "Myanmar",
    "thailand": "Thailand",
    "thai": "Thailand",
    "vietnam": "Vietnam",
    "vietnamese": "Vietnam",
    "philippines": "Philippines",
    "filipino": "Philippines",
    "indonesia": "Indonesia",
    "indonesian": "Indonesia",
    "malaysia": "Malaysia",
    "malaysian": "Malaysia",
    "singapore": "Singapore",
    "singaporean": "Singapore",
    "france": "France",
    "french": "France",
    "germany": "Germany",
    "german": "Germany",
    "britain": "United Kingdom",
    "british": "United Kingdom",
    "uk": "United Kingdom",
    "italy": "Italy",
    "italian": "Italy",
    "spain": "Spain",
    "spanish": "Spain",
    "poland": "Poland",
    "polish": "Poland",
    "greece": "Greece",
    "greek": "Greece",
    "sweden": "Sweden",
    "swedish": "Sweden",
    "norway": "Norway",
    "norwegian": "Norway",
    "denmark": "Denmark",
    "danish": "Denmark",
    "netherlands": "Netherlands",
    "dutch": "Netherlands",
    "belgium": "Belgium",
    "belgian": "Belgium",
    "egypt": "Egypt",
    "egyptian": "Egypt",
    "sudan": "Sudan",
    "sudanese": "Sudan",
    "ethiopia": "Ethiopia",
    "ethiopian": "Ethiopia",
    "nigeria": "Nigeria",
    "nigerian": "Nigeria",
    "south africa": "South Africa",
    "south african": "South Africa",
    "kenya": "Kenya",
    "kenyan": "Kenya",
    "morocco": "Morocco",
    "moroccan": "Morocco",
    "algeria": "Algeria",
    "algerian": "Algeria",
    "libya": "Libya",
    "libyan": "Libya",
    "tunisia": "Tunisia",
    "tunisian": "Tunisia",
    "mexico": "Mexico",
    "mexican": "Mexico",
    "brazil": "Brazil",
    "brazilian": "Brazil",
    "argentina": "Argentina",
    "argentinian": "Argentina",
    "chile": "Chile",
    "chilean": "Chile",
    "colombia": "Colombia",
    "colombian": "Colombia",
    "venezuela": "Venezuela",
    "venezuelan": "Venezuela",
    "peru": "Peru",
    "peruvian": "Peru",
    "ecuador": "Ecuador",
    "ecuadorian": "Ecuador",
    "bolivia": "Bolivia",
    "bolivian": "Bolivia",
    "canada": "Canada",
    "canadian": "Canada",
    "australia": "Australia",
    "australian": "Australia",
    "new zealand": "New Zealand",
    "kiwi": "New Zealand",
    "united states": "United States",
    "america": "United States",
    "american": "United States",
    "usa": "United States",
    "us": "United States",
    "taiwan": "Taiwan",
    "taiwanese": "Taiwan",
    "north korea": "North Korea",
    "south korea": "South Korea",
    "hong kong": "Hong Kong",
    "moscow": "Russia",
    "kyiv": "Ukraine",
    "kiev": "Ukraine"
  },
  "incident_keywords": [
    "attack", "killed", "murder", "shooting", "explosion", "crash", "disaster",
    "terror", "riot", "violence", "accident", "earthquake", "fire", "storm",
    "protest", "assault", "hurricane", "drowning", "death", "injured",
    "outbreak", "virus", "infection", "pandemic", "epidemic", "disease",
    "flu", "covid", "ebola", "zika", "sars", "health", "vaccine", "contagion",
    "war", "conflict", "bombing", "military", "troops", "battle", "invasion",
    "strike", "missile", "drone", "hostage", "kidnap", "arrest"
  ],
  "sources": {
    "bbc": {
      "rss_url": "http://feeds.bbci.co.uk/news/rss.xml",
      "name": "BBC News"
    },
    "fox": {
      "rss_urls": [
        "https://moxie.foxnews.com/google-publisher/world.xml",
        "http://feeds.foxnews.com/foxnews/latest"
      ],
      "name": "Fox News"
    },
    "ap": {
      "base_url": "https://apnews.com/hub/world-news",
      "name": "AP News"
    }
  }
}
